CHANGES.txt
MANIFEST.in
NOTICE
README.rst
setup.py
django_ignoretests2.egg-info/PKG-INFO
django_ignoretests2.egg-info/SOURCES.txt
django_ignoretests2.egg-info/dependency_links.txt
django_ignoretests2.egg-info/entry_points.txt
django_ignoretests2.egg-info/not-zip-safe
django_ignoretests2.egg-info/top_level.txt
ignoretests/__init__.py
ignoretests/jenkins.py